LICENSE
MANIFEST.in
README.md
pyproject.toml
setup.cfg
setup.py
src/quocs_lib.egg-info/PKG-INFO
src/quocs_lib.egg-info/SOURCES.txt
src/quocs_lib.egg-info/dependency_links.txt
src/quocs_lib.egg-info/requires.txt
src/quocs_lib.egg-info/top_level.txt
src/quocslib/Controls.py
src/quocslib/Optimizer.py
src/quocslib/__init__.py
src/quocslib/communication/AllInOneCommunication.py
src/quocslib/communication/__init__.py
src/quocslib/figureofmeritevaluation/AbstractFoM.py
src/quocslib/figureofmeritevaluation/__init__.py
src/quocslib/gradientfreemethods/CMAES.py
src/quocslib/gradientfreemethods/DirectSearchMethod.py
src/quocslib/gradientfreemethods/GradientFreeTemplate.py
src/quocslib/gradientfreemethods/NelderMead.py
src/quocslib/gradientfreemethods/__init__.py
src/quocslib/handleexit/AbstractHandleExit.py
src/quocslib/handleexit/HandleExit.py
src/quocslib/handleexit/__init__.py
src/quocslib/noiseprocesses/noiseprocess.py
src/quocslib/noiseprocesses/ornsteinuhlenbeckprocess.py
src/quocslib/optimalcontrolproblems/IsingModelADProblem.py
src/quocslib/optimalcontrolproblems/IsingModelProblem.py
src/quocslib/optimalcontrolproblems/OneQubitProblem.py
src/quocslib/optimalcontrolproblems/OneQubitProblem_2fields.py
src/quocslib/optimalcontrolproblems/RosenbrockProblem.py
src/quocslib/optimalcontrolproblems/__init__.py
src/quocslib/optimizationalgorithms/ADAlgorithm.py
src/quocslib/optimizationalgorithms/AlgorithmTemplate.py
src/quocslib/optimizationalgorithms/DirectSearchAlgorithm.py
src/quocslib/optimizationalgorithms/GRAPEAlgorithm.py
src/quocslib/optimizationalgorithms/OptimizationAlgorithm.py
src/quocslib/optimizationalgorithms/__init__.py
src/quocslib/optimizationalgorithms/dCRABAlgorithm.py
src/quocslib/optimizationalgorithms/Legacy/ADAlgorithmLegacy.py
src/quocslib/optimizationalgorithms/Legacy/GRAPEAlgorithmLegacy.py
src/quocslib/parameters/BaseParameter.py
src/quocslib/parameters/Parameter.py
src/quocslib/parameters/TimeParameter.py
src/quocslib/parameters/__init__.py
src/quocslib/pulses/BasePulse.py
src/quocslib/pulses/__init__.py
src/quocslib/pulses/basis/Chebyshev.py
src/quocslib/pulses/basis/ChoppedBasis.py
src/quocslib/pulses/basis/DummyBasis.py
