Metadata-Version: 2.1
Name: quocs-lib
Version: 0.0.63
Summary: QuOCS (Quantum Optimal Control Suite) library
Home-page: https://github.com/Quantum-OCS/QuOCS
Author: QuOCS Team
Author-email: quantum.optimal.cs@gmail.com
License: UNKNOWN
Project-URL: Bug Tracker, https://github.com/Quantum-OCS/QuOCS/issues
Platform: UNKNOWN
Classifier: Programming Language :: Python :: 3
Classifier: License :: OSI Approved :: Apache Software License
Classifier: Operating System :: OS Independent
Requires-Python: >=3.6
License-File: LICENSE
